ezmysql/__init__.py
ezmysql/connection_async.py
ezmysql/connection_sync.py
ezmysql/eztool.py
ezmysql/idlog.py
ezmysql-0.9.0.dist-info/METADATA
ezmysql-0.9.0.dist-info/WHEEL
ezmysql-0.9.0.dist-info/top_level.txt
ezmysql-0.9.0.dist-info/RECORD
